Workbook

Sheet Project_Data
A1: Project_ID | B1: Project_Name | C1: Asset_Type | D1: Region | E1: Commissioning_Year | F1: Capacity_MW | G1: Load_Factor_pct | H1: Capex_GBPm | I1: Annual_Revenue_GBPm | J1: Annual_Opex_GBPm | K1: Annual_Carbon_Savings_ktCO2e | L1: Project_Life_Years | M1: Planning_Risk | N1: Grid_Risk | O1: Supply_Chain_Risk | P1: Technology_Readiness | Q1: Development_Status | R1: Expected_ROI_pct | S1: NPV_GBPm | T1: Payback_Years | U1: Jobs_Supported | V1: Policy_Support_Score
A2: EIP-0001 | B2: Offshore Wind Project 001 | C2: Offshore Wind | D2: Wales | E2: 2030 | F2: 1292.9 | G2: 51.8 | H2: 2818.7 | I2: 156.9 | J2: 134.1 | K2: 3720.87 | L2: 29 | M2: Medium | N2: Medium | O2: Low | P2: Commercial | Q2: Operational | R2: 0.2 | S2: -2411 | T2: 123.9 | U2: 1245 | V2: 2
A3: EIP-0002 | B3: CCUS Project 002 | C3: CCUS | D3: UK Midlands | E3: 2028 | F3: 5.5 | G3: 68 | H3: 2740.5 | I3: 436.1 | J3: 193.3 | K3: 24.02 | L3: 25 | M3: Medium | N3: High | O3: High | P3: Demonstration | Q3: Construction | R3: 8.7 | S3: 1232.6 | T3: 11.3 | U3: 10 | V3: 3
A4: EIP-0003 | B4: Gas Infrastructure Project 003 | C4: Gas Infrastructure | D4: East of England | E4: 2027 | F4: 423.9 | G4: 54.7 | H4: 554.2 | I4: 2 | J4: 18.8 | K4: 224.97 | L4: 24 | M4: Low | N4: High | O4: Medium | P4: Commercial | Q4: Operational | R4: -4.4 | S4: -846.8 | T4: 41.7 | U4: 536 | V4: 5
A5: EIP-0004 | B5: Battery Storage Project 004 | C5: Battery Storage | D5: Wales | E5: 2028 | F5: 366.6 | G5: 24.2 | H5: 530.1 | I5: 126.6 | J5: 25.3 | K5: 176.69 | L5: 13 | M5: Medium | N5: Medium | O5: Low | P5: Demonstration | Q5: Operational | R5: 18.2 | S5: 363.3 | T5: 5.2 | U5: 350 | V5: 5
A6: EIP-0005 | B6: Gas Infrastructure Project 005 | C6: Gas Infrastructure | D6: UK North | E6: 2031 | F6: 53.5 | G6: 55.1 | H6: 876.6 | I6: 71.1 | J6: 30.7 | K6: 40.16 | L6: 38 | M6: High | N6: Low | O6: Low | P6: Commercial | Q6: Planning | R6: 5.1 | S6: 230.1 | T6: 21.7 | U6: 57 | V6: 5
A7: EIP-0006 | B7: Battery Storage Project 006 | C7: Battery Storage | D7: East of England | E7: 2035 | F7: 499.2 | G7: 23.8 | H7: 785 | I7: 27.8 | J7: 25.5 | K7: 107.83 | L7: 15 | M7: Medium | N7: Low | O7: Medium | P7: Commercial | Q7: Operational | R7: -0.4 | S7: -761 | T7: 336.7 | U7: 342 | V7: 1
A8: EIP-0007 | B8: Gas Infrastructure Project 007 | C8: Gas Infrastructure | D8: UK Midlands | E8: 2035 | F8: 394.6 | G8: 72 | H8: 316.8 | I8: 53.9 | J8: 13.2 | K8: 176.63 | L8: 37 | M8: Low | N8: Low | O8: High | P8: Early Commercial | Q8: Operational | R8: 11.7 | S8: 710.3 | T8: 7.8 | U8: 251 | V8: 9
A9: EIP-0008 | B9: Gas Infrastructure Project 008 | C9: Gas Infrastructure | D9: Wales | E9: 2033 | F9: 362.3 | G9: 36.3 | H9: 1272.5 | I9: 75.8 | J9: 41 | K9: 149.82 | L9: 39 | M9: High | N9: Low | O9: High | P9: Early Commercial | Q9: Operational | R9: 3.8 | S9: -355.2 | T9: 36.6 | U9: 383 | V9: 5
A10: EIP-0009 | B10: Gas Infrastructure Project 009 | C10: Gas Infrastructure | D10: Scotland | E10: 2032 | F10: 473.9 | G10: 55.5 | H10: 607.2 | I10: 96.4 | J10: 19.2 | K10: 318.26 | L10: 24 | M10: High | N10: Low | O10: Low | P10: Demonstration | Q10: Operational | R10: 12.8 | S10: 783 | T10: 7.9 | U10: 721 | V10: 3
A11: EIP-0010 | B11: Battery Storage Project 010 | C11: Battery Storage | D11: Wales | E11: 2034 | F11: 146.3 | G11: 32.8 | H11: 508.2 | I11: 108.2 | J11: 15.4 | K11: 84.93 | L11: 13 | M11: Low | N11: Medium | O11: Low | P11: Early Commercial | Q11: Construction | R11: 18.8 | S11: 406.4 | T11: 5.5 | U11: 89 | V11: 10
A12: EIP-0011 | B12: Solar PV Project 011 | C12: Solar PV | D12: UK Midlands | E12: 2032 | F12: 412.5 | G12: 17.2 | H12: 621.8 | I12: 127.1 | J12: 12.4 | K12: 243.57 | L12: 25 | M12: Medium | N12: Medium | O12: Medium | P12: Early Commercial | Q12: Operational | R12: 18.1 | S12: 1324.6 | T12: 5.4 | U12: 334 | V12: 8
A13: EIP-0012 | B13: CCUS Project 012 | C13: CCUS | D13: UK Midlands | E13: 2034 | F13: 2 | G13: 73.9 | H13: 791.5 | I13: 134 | J13: 49.3 | K13: 9.47 | L13: 28 | M13: Medium | N13: High | O13: Medium | P13: Commercial | Q13: Early Development | R13: 11.1 | S13: 749.3 | T13: 9.4 | U13: 10 | V13: 1
... A421: EIP-0420 | B421: CCUS Project 420 | C421: CCUS | D421: UK Midlands | E421: 2034 | F421: 5.3 | G421: 75.7 | H421: 1319.2 | I421: 2 | J421: 66.4 | K421: 13.15 | L421: 24 | M421: Low | N421: Low | O421: Medium | P421: Early Commercial | Q421: Planning | R421: -9.5 | S421: -3497.5 | T421: 56.6 | U421: 10 | V421: 9

Sheet Read_Me
A1: Energy Infrastructure Investment & ESG Assessment — Synthetic Dataset
A3: Purpose | B3: Fictional portfolio dataset for demonstrating Excel/data-analysis, investment assessment and stakeholder communication skills.
A4: Records | B4: 420
A5: Asset types | B5: Offshore Wind, Solar PV, Gas Infrastructure, Heat Pumps, Battery Storage, CCUS, Hydrogen
A6: Important | B6: All projects, values and names are synthetic and are not confidential operational data.
A7: Analytical objective | B7: Compare investment opportunities across financial performance, carbon impact, project risk, technology readiness and policy support.
A10: Key field | B10: Purpose
A11: Capacity_MW | B11: Project capacity in MW (asset-specific).
A12: Load_Factor_pct | B12: Expected utilisation/load factor.
A13: Capex_GBPm | B13: Initial capital expenditure in £m.
A14: Annual_Revenue_GBPm | B14: Illustrative annual revenue in £m.
A15: Annual_Opex_GBPm | B15: Illustrative annual operating expenditure in £m.
A16: Annual_Carbon_Savings_ktCO2e | B16: Illustrative annual carbon benefit in ktCO2e.
A17: Planning_Risk | B17: Synthetic planning/development risk.
A18: Grid_Risk | B18: Synthetic grid connection risk.
... A24: Policy_Support_Score | B24: Synthetic 1–10 policy support score.

Sheet Assumptions-What-If Analysis
A1: Metric | B1: Base | C1: Upside | D1: Downside
A2: Combined Scenario Impact | B2: 0 | C2: =SUM(C6:C9) -> 0.19 | D2: =SUM(D6:D9) -> -0.07
A3: Base NPV (£m) | B3: =_xlfn.XLOOKUP(B10,'Data Analysis'!H:H,'Data Analysis'!E:E,0,0) -> 274.84912 | C3: =B3 -> 274.84912 | D3: =B3 -> 274.84912
A4: Scenario NPV (£m) | B4: =B3*(1+B2) -> 274.84912 | C4: =B3*(1+C2) -> 327.07046 | D4: =B3*(1+D2) -> 255.60968
A5: Financial Impact (£m) | B5: =B4-B3 -> 0 | C5: =C4-B3 -> 52.221333 | D5: =D4-B3 -> -19.239439
A6: Revenue Change | B6: 0 | C6: 0.12 | D6: -0.15
A7: Opex Change | B7: 0 | C7: -0.05 | D7: 0.1
A8: Capex Change | B8: 0 | C8: -0.03 | D8: 0.08
A9: Carbon Value Change | B9: 0 | C9: 0.15 | D9: -0.1
A10: Selected Asset | B10: Solar PV

Sheet Data Analysis
A1: Asset Type | B1: Number of Projects | C1: Average Capex (£m) | D1: Average ROI (%) | E1: Average NPV (£m) | F1: Average Carbon Savings (ktCO2e) | H1: Asset Type | I1: High Planning Risk | J1: High Grid Risk | K1: High Supply Chain Risk | L1: % Technology Readiness (Commercial Projects) | M1: Financial Score | N1: Carbon Score | O1: Risk Score | P1: Technology Score | Q1: Overall Attractiveness Score | R1: Helper Column (Average Carbon Savings (ktCO2e) | V1: Asset Type | W1: Risk Profile | X1: Average ROI (%) | Y1: Risk-Return Score
A2: Offshore Wind | B2: =COUNTIF(Project_Data!C:C,'Data Analysis'!A2) -> 72 | C2: =AVERAGEIF(Project_Data!C:C,'Data Analysis'!A2,Project_Data!H:H) -> 2019.4778 | D2: =AVERAGEIF(Project_Data!C:C,'Data Analysis'!A2,Project_Data!R:R) -> 6.7652778 | E2: =AVERAGEIF(Project_Data!C:C,'Data Analysis'!A2,Project_Data!S:S) -> 445.60694 | F2: =AVERAGEIF(Project_Data!C:C,'Data Analysis'!A2,Project_Data!K:K) -> 1481.3874 | H2: Offshore Wind | I2: =COUNTIFS(Project_Data!C:C,'Data Analysis'!H2,Project_Data!M:M,"High")/COUNTIF(Project_Data!C:C,'Data Analysis'!H2) -> 0.18055556 | J2: =COUNTIFS(Project_Data!C:C,'Data Analysis'!H2,Project_Data!N:N,"High")/COUNTIF(Project_Data!C:C,'Data Analysis'!H2) -> 0.19444444 | K2: =COUNTIFS(Project_Data!C:C,'Data Analysis'!H2,Project_Data!O:O,"High")/COUNTIF(Project_Data!C:C,'Data Analysis'!H2) -> 0.20833333 | L2: =COUNTIFS(Project_Data!C:C,'Data Analysis'!A2,Project_Data!P:P,"Commercial")/COUNTIF(Project_Data!C:C,'Data Analysis'!A2) -> 0.26388889 | M2: =ROUND(1+4*(7-AVERAGE(_xlfn.RANK.EQ(D2,$D$2:$D$8,0),_xlfn.RANK.EQ(E2,$E$2:$E$8,0)))/6,0) -> 4 | N2: =ROUND(1+4*(7-_xlfn.RANK.EQ(F2,$F$2:$F$8,0))/6,0) -> 5 | O2: =ROUND(1+4*(7-AVERAGE(_xlfn.RANK.EQ(I2,$I$2:$I$8,1),_xlfn.RANK.EQ(J2,$J$2:$J$8,1),_xlfn.RANK.EQ(K2,$K$2:$K$8,1)))/6,0) -> 2 | P2: =ROUND(1+4*(7-_xlfn.RANK.EQ(L2,$L$2:$L$8,0))/6,0) -> 1 | Q2: =ROUND(AVERAGE(M2:P2),0) -> 3 | R2: Offshore Wind, 1,481.39 kt CO₂e | V2: Offshore Wind | W2: 2 | X2: 6.7652778 | Y2: =Table5[[#This Row],[Average ROI (%)]]/Table5[[#This Row],[Risk Profile]] -> 3.3826389
A3: Solar PV | B3: =COUNTIF(Project_Data!C:C,'Data Analysis'!A3) -> 57 | C3: =AVERAGEIF(Project_Data!C:C,'Data Analysis'!A3,Project_Data!H:H) -> 368.81053 | D3: =AVERAGEIF(Project_Data!C:C,'Data Analysis'!A3,Project_Data!R:R) -> 9.5561404 | E3: =AVERAGEIF(Project_Data!C:C,'Data Analysis'!A3,Project_Data!S:S) -> 274.84912 | F3: =AVERAGEIF(Project_Data!C:C,'Data Analysis'!A3,Project_Data!K:K) -> 138.43421 | H3: Solar PV | I3: =COUNTIFS(Project_Data!C:C,'Data Analysis'!H3,Project_Data!M:M,"High")/COUNTIF(Project_Data!C:C,'Data Analysis'!H3) -> 0.21052632 | J3: =COUNTIFS(Project_Data!C:C,'Data Analysis'!H3,Project_Data!N:N,"High")/COUNTIF(Project_Data!C:C,'Data Analysis'!H3) -> 0.10526316 | K3: =COUNTIFS(Project_Data!C:C,'Data Analysis'!H3,Project_Data!O:O,"High")/COUNTIF(Project_Data!C:C,'Data Analysis'!H3) -> 0.14035088 | L3: =COUNTIFS(Project_Data!C:C,'Data Analysis'!A3,Project_Data!P:P,"Commercial")/COUNTIF(Project_Data!C:C,'Data Analysis'!A3) -> 0.35087719 | M3: =ROUND(1+4*(7-AVERAGE(_xlfn.RANK.EQ(D3,$D$2:$D$8,0),_xlfn.RANK.EQ(E3,$E$2:$E$8,0)))/6,0) -> 4 | N3: =ROUND(1+4*(7-_xlfn.RANK.EQ(F3,$F$2:$F$8,0))/6,0) -> 3 | O3: =ROUND(1+4*(7-AVERAGE(_xlfn.RANK.EQ(I3,$I$2:$I$8,1),_xlfn.RANK.EQ(J3,$J$2:$J$8,1),_xlfn.RANK.EQ(K3,$K$2:$K$8,1)))/6,0) -> 3 | P3: =ROUND(1+4*(7-_xlfn.RANK.EQ(L3,$L$2:$L$8,0))/6,0) -> 4 | Q3: =ROUND(AVERAGE(M3:P3),0) -> 4 | R3: Solar PV, 138.43 kt CO₂e | V3: Battery Storage | W3: 3 | X3: 9.8533333 | Y3: =Table5[[#This Row],[Average ROI (%)]]/Table5[[#This Row],[Risk Profile]] -> 3.2844444
A4: Gas Infrastructure | B4: =COUNTIF(Project_Data!C:C,'Data Analysis'!A4) -> 65 | C4: =AVERAGEIF(Project_Data!C:C,'Data Analysis'!A4,Project_Data!H:H) -> 777.88308 | D4: =AVERAGEIF(Project_Data!C:C,'Data Analysis'!A4,Project_Data!R:R) -> 5.2307692 | E4: =AVERAGEIF(Project_Data!C:C,'Data Analysis'!A4,Project_Data!S:S) -> 115.68769 | F4: =AVERAGEIF(Project_Data!C:C,'Data Analysis'!A4,Project_Data!K:K) -> 215.50308 | H4: Gas Infrastructure | I4: =COUNTIFS(Project_Data!C:C,'Data Analysis'!H4,Project_Data!M:M,"High")/COUNTIF(Project_Data!C:C,'Data Analysis'!H4) -> 0.13846154 | J4: =COUNTIFS(Project_Data!C:C,'Data Analysis'!H4,Project_Data!N:N,"High")/COUNTIF(Project_Data!C:C,'Data Analysis'!H4) -> 0.16923077 | K4: =COUNTIFS(Project_Data!C:C,'Data Analysis'!H4,Project_Data!O:O,"High")/COUNTIF(Project_Data!C:C,'Data Analysis'!H4) -> 0.18461538 | L4: =COUNTIFS(Project_Data!C:C,'Data Analysis'!A4,Project_Data!P:P,"Commercial")/COUNTIF(Project_Data!C:C,'Data Analysis'!A4) -> 0.29230769 | M4: =ROUND(1+4*(7-AVERAGE(_xlfn.RANK.EQ(D4,$D$2:$D$8,0),_xlfn.RANK.EQ(E4,$E$2:$E$8,0)))/6,0) -> 3 | N4: =ROUND(1+4*(7-_xlfn.RANK.EQ(F4,$F$2:$F$8,0))/6,0) -> 4 | O4: =ROUND(1+4*(7-AVERAGE(_xlfn.RANK.EQ(I4,$I$2:$I$8,1),_xlfn.RANK.EQ(J4,$J$2:$J$8,1),_xlfn.RANK.EQ(K4,$K$2:$K$8,1)))/6,0) -> 3 | P4: =ROUND(1+4*(7-_xlfn.RANK.EQ(L4,$L$2:$L$8,0))/6,0) -> 3 | Q4: =ROUND(AVERAGE(M4:P4),0) -> 3 | R4: Gas Infrastructure, 215.50 kt CO₂e | V4: Solar PV | W4: 3 | X4: 9.5561404 | Y4: =Table5[[#This Row],[Average ROI (%)]]/Table5[[#This Row],[Risk Profile]] -> 3.1853801
A5: Heat Pumps | B5: =COUNTIF(Project_Data!C:C,'Data Analysis'!A5) -> 51 | C5: =AVERAGEIF(Project_Data!C:C,'Data Analysis'!A5,Project_Data!H:H) -> 240.36275 | D5: =AVERAGEIF(Project_Data!C:C,'Data Analysis'!A5,Project_Data!R:R) -> 6.527451 | E5: =AVERAGEIF(Project_Data!C:C,'Data Analysis'!A5,Project_Data!S:S) -> -29.65098 | F5: =AVERAGEIF(Project_Data!C:C,'Data Analysis'!A5,Project_Data!K:K) -> 72.581569 | H5: Heat Pumps | I5: =COUNTIFS(Project_Data!C:C,'Data Analysis'!H5,Project_Data!M:M,"High")/COUNTIF(Project_Data!C:C,'Data Analysis'!H5) -> 0.098039216 | J5: =COUNTIFS(Project_Data!C:C,'Data Analysis'!H5,Project_Data!N:N,"High")/COUNTIF(Project_Data!C:C,'Data Analysis'!H5) -> 0.17647059 | K5: =COUNTIFS(Project_Data!C:C,'Data Analysis'!H5,Project_Data!O:O,"High")/COUNTIF(Project_Data!C:C,'Data Analysis'!H5) -> 0.11764706 | L5: =COUNTIFS(Project_Data!C:C,'Data Analysis'!A5,Project_Data!P:P,"Commercial")/COUNTIF(Project_Data!C:C,'Data Analysis'!A5) -> 0.43137255 | M5: =ROUND(1+4*(7-AVERAGE(_xlfn.RANK.EQ(D5,$D$2:$D$8,0),_xlfn.RANK.EQ(E5,$E$2:$E$8,0)))/6,0) -> 3 | N5: =ROUND(1+4*(7-_xlfn.RANK.EQ(F5,$F$2:$F$8,0))/6,0) -> 2 | O5: =ROUND(1+4*(7-AVERAGE(_xlfn.RANK.EQ(I5,$I$2:$I$8,1),_xlfn.RANK.EQ(J5,$J$2:$J$8,1),_xlfn.RANK.EQ(K5,$K$2:$K$8,1)))/6,0) -> 4 | P5: =ROUND(1+4*(7-_xlfn.RANK.EQ(L5,$L$2:$L$8,0))/6,0) -> 5 | Q5: =ROUND(AVERAGE(M5:P5),0) -> 4 | R5: Heat Pumps, 72.58 kt CO₂e | V5: Gas Infrastructure | W5: 3 | X5: 5.2307692 | Y5: =Table5[[#This Row],[Average ROI (%)]]/Table5[[#This Row],[Risk Profile]] -> 1.7435897
A6: Battery Storage | B6: =COUNTIF(Project_Data!C:C,'Data Analysis'!A6) -> 60 | C6: =AVERAGEIF(Project_Data!C:C,'Data Analysis'!A6,Project_Data!H:H) -> 545.365 | D6: =AVERAGEIF(Project_Data!C:C,'Data Analysis'!A6,Project_Data!R:R) -> 9.8533333 | E6: =AVERAGEIF(Project_Data!C:C,'Data Analysis'!A6,Project_Data!S:S) -> 20.211667 | F6: =AVERAGEIF(Project_Data!C:C,'Data Analysis'!A6,Project_Data!K:K) -> 102.22983 | H6: Battery Storage | I6: =COUNTIFS(Project_Data!C:C,'Data Analysis'!H6,Project_Data!M:M,"High")/COUNTIF(Project_Data!C:C,'Data Analysis'!H6) -> 0.2 | J6: =COUNTIFS(Project_Data!C:C,'Data Analysis'!H6,Project_Data!N:N,"High")/COUNTIF(Project_Data!C:C,'Data Analysis'!H6) -> 0.13333333 | K6: =COUNTIFS(Project_Data!C:C,'Data Analysis'!H6,Project_Data!O:O,"High")/COUNTIF(Project_Data!C:C,'Data Analysis'!H6) -> 0.21666667 | L6: =COUNTIFS(Project_Data!C:C,'Data Analysis'!A6,Project_Data!P:P,"Commercial")/COUNTIF(Project_Data!C:C,'Data Analysis'!A6) -> 0.28333333 | M6: =ROUND(1+4*(7-AVERAGE(_xlfn.RANK.EQ(D6,$D$2:$D$8,0),_xlfn.RANK.EQ(E6,$E$2:$E$8,0)))/6,0) -> 4 | N6: =ROUND(1+4*(7-_xlfn.RANK.EQ(F6,$F$2:$F$8,0))/6,0) -> 2 | O6: =ROUND(1+4*(7-AVERAGE(_xlfn.RANK.EQ(I6,$I$2:$I$8,1),_xlfn.RANK.EQ(J6,$J$2:$J$8,1),_xlfn.RANK.EQ(K6,$K$2:$K$8,1)))/6,0) -> 3 | P6: =ROUND(1+4*(7-_xlfn.RANK.EQ(L6,$L$2:$L$8,0))/6,0) -> 2 | Q6: =ROUND(AVERAGE(M6:P6),0) -> 3 | R6: Battery Storage, 102.23 kt CO₂e | V6: Hydrogen | W6: 2 | X6: 3.28 | Y6: =Table5[[#This Row],[Average ROI (%)]]/Table5[[#This Row],[Risk Profile]] -> 1.64
A7: CCUS | B7: =COUNTIF(Project_Data!C:C,'Data Analysis'!A7) -> 60 | C7: =AVERAGEIF(Project_Data!C:C,'Data Analysis'!A7,Project_Data!H:H) -> 1663.615 | D7: =AVERAGEIF(Project_Data!C:C,'Data Analysis'!A7,Project_Data!R:R) -> -0.3 | E7: =AVERAGEIF(Project_Data!C:C,'Data Analysis'!A7,Project_Data!S:S) -> -1657.2317 | F7: =AVERAGEIF(Project_Data!C:C,'Data Analysis'!A7,Project_Data!K:K) -> 16.087 | H7: CCUS | I7: =COUNTIFS(Project_Data!C:C,'Data Analysis'!H7,Project_Data!M:M,"High")/COUNTIF(Project_Data!C:C,'Data Analysis'!H7) -> 0.2 | J7: =COUNTIFS(Project_Data!C:C,'Data Analysis'!H7,Project_Data!N:N,"High")/COUNTIF(Project_Data!C:C,'Data Analysis'!H7) -> 0.16666667 | K7: =COUNTIFS(Project_Data!C:C,'Data Analysis'!H7,Project_Data!O:O,"High")/COUNTIF(Project_Data!C:C,'Data Analysis'!H7) -> 0.16666667 | L7: =COUNTIFS(Project_Data!C:C,'Data Analysis'!A7,Project_Data!P:P,"Commercial")/COUNTIF(Project_Data!C:C,'Data Analysis'!A7) -> 0.26666667 | M7: =ROUND(1+4*(7-AVERAGE(_xlfn.RANK.EQ(D7,$D$2:$D$8,0),_xlfn.RANK.EQ(E7,$E$2:$E$8,0)))/6,0) -> 1 | N7: =ROUND(1+4*(7-_xlfn.RANK.EQ(F7,$F$2:$F$8,0))/6,0) -> 1 | O7: =ROUND(1+4*(7-AVERAGE(_xlfn.RANK.EQ(I7,$I$2:$I$8,1),_xlfn.RANK.EQ(J7,$J$2:$J$8,1),_xlfn.RANK.EQ(K7,$K$2:$K$8,1)))/6,0) -> 3 | P7: =ROUND(1+4*(7-_xlfn.RANK.EQ(L7,$L$2:$L$8,0))/6,0) -> 2 | Q7: =ROUND(AVERAGE(M7:P7),0) -> 2 | R7: CCUS, 16.09 kt CO₂e | V7: Heat Pumps | W7: 4 | X7: 6.527451 | Y7: =Table5[[#This Row],[Average ROI (%)]]/Table5[[#This Row],[Risk Profile]] -> 1.6318627
A8: Hydrogen | B8: =COUNTIF(Project_Data!C:C,'Data Analysis'!A8) -> 55 | C8: =AVERAGEIF(Project_Data!C:C,'Data Analysis'!A8,Project_Data!H:H) -> 1456.8364 | D8: =AVERAGEIF(Project_Data!C:C,'Data Analysis'!A8,Project_Data!R:R) -> 3.28 | E8: =AVERAGEIF(Project_Data!C:C,'Data Analysis'!A8,Project_Data!S:S) -> -784.66 | F8: =AVERAGEIF(Project_Data!C:C,'Data Analysis'!A8,Project_Data!K:K) -> 921.79909 | H8: Hydrogen | I8: =COUNTIFS(Project_Data!C:C,'Data Analysis'!H8,Project_Data!M:M,"High")/COUNTIF(Project_Data!C:C,'Data Analysis'!H8) -> 0.12727273 | J8: =COUNTIFS(Project_Data!C:C,'Data Analysis'!H8,Project_Data!N:N,"High")/COUNTIF(Project_Data!C:C,'Data Analysis'!H8) -> 0.21818182 | K8: =COUNTIFS(Project_Data!C:C,'Data Analysis'!H8,Project_Data!O:O,"High")/COUNTIF(Project_Data!C:C,'Data Analysis'!H8) -> 0.25454545 | L8: =COUNTIFS(Project_Data!C:C,'Data Analysis'!A8,Project_Data!P:P,"Commercial")/COUNTIF(Project_Data!C:C,'Data Analysis'!A8) -> 0.30909091 | M8: =ROUND(1+4*(7-AVERAGE(_xlfn.RANK.EQ(D8,$D$2:$D$8,0),_xlfn.RANK.EQ(E8,$E$2:$E$8,0)))/6,0) -> 2 | N8: =ROUND(1+4*(7-_xlfn.RANK.EQ(F8,$F$2:$F$8,0))/6,0) -> 4 | O8: =ROUND(1+4*(7-AVERAGE(_xlfn.RANK.EQ(I8,$I$2:$I$8,1),_xlfn.RANK.EQ(J8,$J$2:$J$8,1),_xlfn.RANK.EQ(K8,$K$2:$K$8,1)))/6,0) -> 2 | P8: =ROUND(1+4*(7-_xlfn.RANK.EQ(L8,$L$2:$L$8,0))/6,0) -> 4 | Q8: =ROUND(AVERAGE(M8:P8),0) -> 3 | R8: Hydrogen, 921.80 kt CO₂e | V8: CCUS | W8: 3 | X8: -0.3 | Y8: =Table5[[#This Row],[Average ROI (%)]]/Table5[[#This Row],[Risk Profile]] -> -0.1
